aviv_aws_costexplorer/__init__.py
aviv_aws_costexplorer/base.py
aviv_aws_costexplorer/budgets.py
aviv_aws_costexplorer/costcategory.py
aviv_aws_costexplorer/costexplorer.py
aviv_aws_costexplorer/costreporter.py
aviv_aws_costexplorer/datastore.py
aviv_aws_costexplorer/filters.py
aviv_aws_costexplorer/types/__init__.py
aviv_aws_costexplorer/types/cau.py
aviv_aws_costexplorer/types/costcategories.py
aviv_aws_costexplorer/types/costcategory.py
aviv_aws_costexplorer-0.2.3.dist-info/LICENSE
aviv_aws_costexplorer-0.2.3.dist-info/METADATA
aviv_aws_costexplorer-0.2.3.dist-info/WHEEL
aviv_aws_costexplorer-0.2.3.dist-info/top_level.txt
aviv_aws_costexplorer-0.2.3.dist-info/RECORD
