Metadata-Version: 2.1
Name: aviv-aws-costexplorer
Version: 0.2.3
Summary: Aviv AWS CostExplorer python library
Home-page: https://github.com/aviv-group/aviv-aws-costexplorer
Author: Jules Clement
Author-email: jules.clement@aviv-group.com
License: UNKNOWN
Platform: UNKNOWN
Classifier: Development Status :: 4 - Beta
Classifier: Intended Audience :: Developers
Classifier: Intended Audience :: Information Technology
Classifier: Intended Audience :: System Administrators
Classifier: License :: OSI Approved :: MIT License
Classifier: Programming Language :: Python :: 3 :: Only
Classifier: Programming Language :: Python :: 3.8
Classifier: Operating System :: OS Independent
Classifier: Topic :: Utilities
Classifier: Topic :: Office/Business
Classifier: Topic :: Office/Business :: Financial
Classifier: Topic :: Office/Business :: Financial :: Accounting
Classifier: Topic :: System
Classifier: Topic :: System :: Logging
Classifier: Topic :: System :: Monitoring
Classifier: Topic :: System :: Systems Administration
Classifier: Typing :: Typed
Requires-Python: >=3.8
License-File: LICENSE
Requires-Dist: boto3 (>=1.17.43)
Requires-Dist: botocore (>=1.20.43)
Requires-Dist: pydantic (>=1.8.2)
Requires-Dist: python-dateutil (>=2.8.0)
Provides-Extra: datastore
Requires-Dist: awswrangler (>=2.6.0) ; extra == 'datastore'
Requires-Dist: pandas (>=1.2.3) ; extra == 'datastore'
Requires-Dist: numpy (>=1.20.0) ; extra == 'datastore'
